streamstraight_server/__init__.py
streamstraight_server/constants.py
streamstraight_server/jwt_token.py
streamstraight_server/main.py
streamstraight_server/options.py
streamstraight_server/protocol.py
streamstraight_server/py.typed
streamstraight_server/server.py
streamstraight_server/utils.py
streamstraight_server-0.2.10.dist-info/METADATA
streamstraight_server-0.2.10.dist-info/WHEEL
streamstraight_server-0.2.10.dist-info/top_level.txt
streamstraight_server-0.2.10.dist-info/RECORD
