Metadata-Version: 2.4
Name: streamstraight-server
Version: 0.2.10
Summary: Python server SDK for streaming data into Streamstraight.
Author-email: Streamstraight <support@streamstraight.com>
License-Expression: MIT
Project-URL: Homepage, https://www.streamstraight.com
Project-URL: Documentation, https://docs.streamstraight.com
Project-URL: Repository, https://github.com/streamstraight/streamstraight
Project-URL: Issues, https://github.com/streamstraight/streamstraight/issues
Keywords: streaming,socket.io,websockets,sdk,llm,streamstraight
Requires-Python: >=3.10
Requires-Dist: httpx<0.29,>=0.27
Requires-Dist: aiohttp>=3.9
Requires-Dist: python-socketio<6,>=5.11.0
Requires-Dist: anyio>=4.0
Requires-Dist: typing-extensions>=4.8; python_version < "3.11"
